mlops_test/__init__.py
mlops_test/test_api.py
mlops_test-0.1.3.dist-info/WHEEL
mlops_test-0.1.3.dist-info/METADATA
mlops_test-0.1.3.dist-info/RECORD
